gitlab_job_exec/__init__.py
gitlab_job_exec/cli.py
tests/__init__.py
tests/test_cli.py
tests/test_gitlab_job_exec.py
gitlab_job_exec-1.5.108.dist-info/LICENSE
gitlab_job_exec-1.5.108.dist-info/METADATA
gitlab_job_exec-1.5.108.dist-info/WHEEL
gitlab_job_exec-1.5.108.dist-info/entry_points.txt
gitlab_job_exec-1.5.108.dist-info/top_level.txt
gitlab_job_exec-1.5.108.dist-info/RECORD
