Metadata-Version: 2.1
Name: gitlab-job-exec
Version: 1.5.108
Summary: Execute GitLab-CI docker jobs
Home-page: https://gitlab.com/uncrns/gitlab-job-exec
Author: Uncrns
Author-email: uncrns.devs@gmail.com
License: UNKNOWN
Platform: UNKNOWN
Classifier: Development Status :: 2 - Pre-Alpha
Classifier: Environment :: Console
Classifier: Intended Audience :: Developers
Classifier: License :: OSI Approved :: MIT License
Classifier: Natural Language :: English
Classifier: Operating System :: POSIX
Classifier: Programming Language :: Python
Classifier: Programming Language :: Python :: 3
Requires-Python: >=3.6
Requires-Dist: ConfigArgParse
Requires-Dist: docker
Requires-Dist: dpath (>=2.1.4)
Requires-Dist: pyyaml
Requires-Dist: requests
Requires-Dist: requests-file
